[
  {
    "code": "GB 15618-2018",
    "clause": "表1",
    "title": "土壤环境质量标准 农用地",
    "category": "标准",
    "content": "农用地土壤污染风险筛选值（基本项目）：镉(Cd) pH≤5.5: 0.3mg/kg, 5.5<pH≤6.5: 0.4mg/kg, 6.5<pH≤7.5: 0.6mg/kg, pH>7.5: 0.8mg/kg。汞(Hg) pH≤5.5: 1.3mg/kg, 5.5<pH≤6.5: 1.8mg/kg, 6.5<pH≤7.5: 2.4mg/kg, pH>7.5: 3.4mg/kg。砷(As) pH≤5.5: 40mg/kg, 5.5<pH≤6.5: 40mg/kg, 6.5<pH≤7.5: 30mg/kg, pH>7.5: 25mg/kg。铅(Pb) pH≤5.5: 70mg/kg, 5.5<pH≤6.5: 90mg/kg, 6.5<pH≤7.5: 120mg/kg, pH>7.5: 170mg/kg。铬(Cr) pH≤5.5: 150mg/kg, 5.5<pH≤6.5: 150mg/kg, 6.5<pH≤7.5: 200mg/kg, pH>7.5: 250mg/kg。铜(Cu) pH≤5.5: 50mg/kg, 5.5<pH≤6.5: 50mg/kg, 6.5<pH≤7.5: 100mg/kg, pH>7.5: 100mg/kg。镍(Ni) pH≤5.5: 60mg/kg, 5.5<pH≤6.5: 70mg/kg, 6.5<pH≤7.5: 100mg/kg, pH>7.5: 190mg/kg。锌(Zn) pH≤5.5: 200mg/kg, 5.5<pH≤6.5: 200mg/kg, 6.5<pH≤7.5: 250mg/kg, pH>7.5: 300mg/kg。",
    "explanation": "农用地标准按pH分级，酸性土壤污染风险更高（限值更严）。农用地只有筛选值（风险筛选），没有管控值概念。"
  }
]
